{
  "cohort_id": "EVP-7",
  "results": [
    {
      "blocked_reason": [
        "windows_missing_fcntl"
      ],
      "bug_id": "1",
      "date": "2026-06-13",
      "decision": "do_not_admit_environment_blocked",
      "fixed_result": "import_error_before_target_test",
      "notes": "Both checkouts completed. The initial run missed PYTHONPATH=lib; rerunning with PYTHONPATH=lib reached a Windows-only blocker because Ansible imports fcntl. No compatibility shim, dependency install, or checkout edit was performed.",
      "probe_status": "f2p_blocked_windows_posix_import",
      "project": "ansible",
      "run_command": "PYTHONPATH=lib python -m pytest test/units/galaxy/test_collection.py::test_verify_collections_no_version",
      "source": "BugsInPy",
      "task_id": "bugsinpy_ansible_1",
      "test_file": "test/units/galaxy/test_collection.py",
      "versions": {
        "buggy": {
          "checkout": "completed",
          "git_head": "25c5388fde",
          "result": "import_error_before_target_test"
        },
        "fixed": {
          "checkout": "completed",
          "git_head": "25c5388fde",
          "result": "import_error_before_target_test"
        }
      }
    },
    {
      "blocked_reason": [
        "pydantic_v2_import_incompatibility"
      ],
      "bug_id": "4",
      "date": "2026-06-13",
      "decision": "do_not_admit_environment_blocked",
      "fixed_result": "collection_error_before_target_test",
      "notes": "Both buggy and fixed checkouts completed, but the target pytest command failed during collection because this legacy FastAPI version imports under the current Pydantic v2 environment. No dependency install or checkout edit was performed.",
      "probe_status": "f2p_blocked_dependency_environment",
      "project": "fastapi",
      "run_command": "python -m pytest tests/test_param_in_path_and_dependency.py::test_reused_param",
      "source": "BugsInPy",
      "task_id": "bugsinpy_fastapi_4",
      "test_file": "tests/test_param_in_path_and_dependency.py",
      "versions": {
        "buggy": {
          "checkout": "completed",
          "git_head": "7ccd81f70",
          "result": "collection_error_before_target_test"
        },
        "fixed": {
          "checkout": "completed",
          "git_head": "7ccd81f70",
          "result": "collection_error_before_target_test"
        }
      }
    },
    {
      "blocked_reason": [
        "missing_tornado_dependency"
      ],
      "bug_id": "1",
      "date": "2026-06-13",
      "decision": "do_not_admit_environment_blocked",
      "fixed_result": "import_error_before_target_test",
      "notes": "Both checkouts completed. Existing inspect.ArgSpec/getargspec runtime compatibility passed the Python 3.11 import gap, but both versions then failed because tornado is not installed in the current environment. No dependency install or checkout edit was performed.",
      "probe_status": "f2p_blocked_dependency_environment",
      "project": "luigi",
      "run_command": "python -m pytest test/server_test.py::MetricsHandlerTest::test_get with existing inspect runtime compatibility",
      "source": "BugsInPy",
      "task_id": "bugsinpy_luigi_1",
      "test_file": "test/server_test.py",
      "versions": {
        "buggy": {
          "checkout": "completed",
          "git_head": "1164eb6b",
          "result": "import_error_before_target_test"
        },
        "fixed": {
          "checkout": "completed",
          "git_head": "1164eb6b",
          "result": "import_error_before_target_test"
        }
      }
    },
    {
      "blocked_reason": [
        "existing_incomplete_checkout",
        "native_extension_import_blocker"
      ],
      "bug_id": "1",
      "date": "2026-06-13",
      "decision": "do_not_admit_existing_blocker",
      "fixed_result": "not_rerun",
      "notes": "Historical matplotlib_1 workspace exists but the buggy checkout lacks the target test file; this task already has a native-extension import blocker and was not rebuilt in this F2P-only batch.",
      "probe_status": "f2p_blocked_existing_incomplete_native_probe",
      "project": "matplotlib",
      "run_command": "python -m pytest lib/matplotlib/tests/test_bbox_tight.py::test_noop_tight_bbox",
      "source": "BugsInPy",
      "task_id": "bugsinpy_matplotlib_1",
      "test_file": "lib/matplotlib/tests/test_bbox_tight.py",
      "versions": {
        "buggy": {
          "checkout": "existing_incomplete",
          "git_head": null,
          "result": "target_test_file_missing"
        },
        "fixed": {
          "checkout": "reused_existing",
          "git_head": "c404d1f716",
          "result": "not_rerun"
        }
      }
    },
    {
      "blocked_reason": [
        "missing_aiofiles_dependency"
      ],
      "bug_id": "2",
      "date": "2026-06-13",
      "decision": "do_not_admit_environment_blocked",
      "fixed_result": "import_error_before_target_test",
      "notes": "Both buggy and fixed checkouts completed, but the target pytest command failed while loading tests/conftest.py because aiofiles is not installed in the current environment. No dependency install or checkout edit was performed.",
      "probe_status": "f2p_blocked_dependency_environment",
      "project": "sanic",
      "run_command": "python -m pytest tests/test_app.py::test_asyncio_server_start_serving",
      "source": "BugsInPy",
      "task_id": "bugsinpy_sanic_2",
      "test_file": "tests/test_app.py",
      "versions": {
        "buggy": {
          "checkout": "completed",
          "git_head": "ba9b4329",
          "result": "import_error_before_target_test"
        },
        "fixed": {
          "checkout": "completed",
          "git_head": "ba9b4329",
          "result": "import_error_before_target_test"
        }
      }
    },
    {
      "blocked_reason": [
        "missing_twisted_dependency"
      ],
      "bug_id": "2",
      "date": "2026-06-13",
      "decision": "do_not_admit_environment_blocked",
      "fixed_result": "import_error_before_target_test",
      "notes": "Both buggy and fixed checkouts completed, but the target unittest command failed while importing Scrapy because twisted is not installed in the current environment. No dependency install or checkout edit was performed.",
      "probe_status": "f2p_blocked_dependency_environment",
      "project": "scrapy",
      "run_command": "python -m unittest -q tests.test_utils_datatypes.LocalCacheTest.test_cache_without_limit",
      "source": "BugsInPy",
      "task_id": "bugsinpy_scrapy_2",
      "test_file": "tests/test_utils_datatypes.py",
      "versions": {
        "buggy": {
          "checkout": "completed",
          "git_head": "f02c3d1dc",
          "result": "import_error_before_target_test"
        },
        "fixed": {
          "checkout": "completed",
          "git_head": "f02c3d1dc",
          "result": "import_error_before_target_test"
        }
      }
    },
    {
      "blocked_reason": [
        "existing_project_level_p2p_timeout"
      ],
      "bug_id": "1",
      "date": "2026-06-13",
      "decision": "f2p_established_but_not_admitted",
      "fixed_result": "pass",
      "notes": "Reused existing checkout and reran the target unittest with the documented Windows selector event loop policy. Buggy fails and fixed passes, but the task already has a project-level P2P-broad timeout blocker and is not admitted.",
      "probe_status": "f2p_established_existing_p2p_timeout",
      "project": "tornado",
      "run_command": "python -c \"import asyncio, runpy, sys; asyncio.set_event_loop_policy(asyncio.WindowsSelectorEventLoopPolicy()); sys.argv=['python -m unittest','-q','tornado.test.websocket_test.WebSocketTest.test_nodelay']; runpy.run_module('unittest', run_name='__main__')\"",
      "source": "BugsInPy",
      "task_id": "bugsinpy_tornado_1",
      "test_file": "tornado/test/websocket_test.py",
      "versions": {
        "buggy": {
          "checkout": "reused_existing",
          "git_head": "6a5a0bfa",
          "result": "fail"
        },
        "fixed": {
          "checkout": "reused_existing",
          "git_head": "6a5a0bfa",
          "result": "pass"
        }
      }
    },
    {
      "blocked_reason": [
        "github_clone_tls_failure_repaired_with_local_clone",
        "corrected_policy_project_level_p2p_timeout"
      ],
      "bug_id": "10",
      "date": "2026-06-14",
      "decision": "do_not_admit_corrected_policy_p2p_timeout",
      "fixed_result": "pass",
      "notes": "Initial BugsInPy checkout reached a GitHub clone TLS termination and produced no marker files despite exit code 0. The workspace was reconstructed from an existing local youtube-dl Git checkout after verifying both ydl10 commits were present, following the BugsInPy reset/copy-test-file flow without dependency install, source edit, or shim. The target unittest then failed on buggy and passed on fixed, establishing F2P. Corrected-policy project-level P2P-broad dry-run passed, but the real builder exceeded the 40 minute outer budget, produced no manifest, and was stopped with a residual unittest subprocess.",
      "probe_status": "f2p_established_corrected_policy_p2p_timeout",
      "project": "youtube-dl",
      "run_command": "python -m unittest -q test.test_utils.TestUtil.test_js_to_json_realworld",
      "source": "BugsInPy",
      "task_id": "bugsinpy_youtube-dl_10",
      "test_file": "test/test_utils.py",
      "versions": {
        "buggy": {
          "checkout": "local_clone_after_github_tls_failure",
          "git_head": "85d586617750d38d742a24f141b099f6b898d269",
          "result": "fail"
        },
        "fixed": {
          "checkout": "local_clone_after_github_tls_failure",
          "git_head": "85d586617750d38d742a24f141b099f6b898d269_with_fixed_files",
          "result": "pass"
        }
      }
    },
    {
      "blocked_reason": [],
      "bug_id": "11",
      "candidate_validation_report": "docs/experiments/youtubedl11_candidate_validation.md",
      "date": "2026-06-14",
      "decision": "admitted_to_p2p_broad_main",
      "fixed_result": "pass",
      "notes": "Both checkouts completed and the target pure-utils unittest produced the expected buggy error and fixed pass. A later project-level P2P-broad run produced 160 retained P2P tests with youtube_dl_dynamic_download_nodeid_exclusion_v1, and four candidate records passed retained-oracle and P2P-broad validation before admission.",
      "p2p_broad_manifest": "data/p2p_scopes/bugsinpy_youtube-dl_11_p2p_broad.json",
      "probe_status": "admitted_p2p_broad_main",
      "project": "youtube-dl",
      "run_command": "python -m unittest -q test.test_utils.TestUtil.test_str_to_int",
      "source": "BugsInPy",
      "task_id": "bugsinpy_youtube-dl_11",
      "test_file": "test/test_utils.py",
      "versions": {
        "buggy": {
          "checkout": "completed",
          "git_head": "b568561eb",
          "result": "fail"
        },
        "fixed": {
          "checkout": "completed",
          "git_head": "b568561eb",
          "result": "pass"
        }
      }
    },
    {
      "blocked_reason": [
        "checkout_timeout"
      ],
      "bug_id": "13",
      "date": "2026-06-14",
      "decision": "do_not_admit_checkout_timeout",
      "fixed_result": "not_attempted",
      "notes": "The local BugsInPy checkout tool was available through the retained archive, but the buggy checkout exceeded the 10 minute bounded probe window and produced only an incomplete .git directory without bugsinpy_run_test.sh. The residual bash process was stopped and the incomplete youtube-dl_13 workspace was removed. No fixed checkout, F2P run, dependency install, or checkout edit was performed.",
      "probe_status": "f2p_blocked_checkout_timeout",
      "project": "youtube-dl",
      "run_command": "python -m unittest -q test.test_utils.TestUtil.test_urljoin",
      "source": "BugsInPy",
      "task_id": "bugsinpy_youtube-dl_13",
      "test_file": "test/test_utils.py",
      "versions": {
        "buggy": {
          "checkout": "timeout_incomplete_removed",
          "git_head": null,
          "result": "not_run"
        },
        "fixed": {
          "checkout": "not_attempted",
          "git_head": null,
          "result": "not_run"
        }
      }
    },
    {
      "blocked_reason": [],
      "bug_id": "16",
      "candidate_validation_report": "docs/experiments/youtubedl16_candidate_validation.md",
      "date": "2026-06-14",
      "decision": "admitted_to_p2p_broad_main",
      "fixed_result": "pass",
      "notes": "Local clone checkout followed the BugsInPy reset/copy-test-file flow after GitHub clone instability was observed in earlier probes. The target pure-utils unittest produced the expected buggy error and fixed pass. A later project-level P2P-broad run produced 147 retained P2P tests with youtube_dl_dynamic_download_nodeid_exclusion_v1, and four candidate records passed retained-oracle and P2P-broad validation before admission.",
      "p2p_broad_manifest": "data/p2p_scopes/bugsinpy_youtube-dl_16_p2p_broad.json",
      "probe_status": "admitted_p2p_broad_main",
      "project": "youtube-dl",
      "run_command": "python -m unittest -q test.test_utils.TestUtil.test_dfxp2srt",
      "source": "BugsInPy",
      "task_id": "bugsinpy_youtube-dl_16",
      "test_file": "test/test_utils.py",
      "versions": {
        "buggy": {
          "checkout": "local_clone",
          "git_head": "68d43a61b552007a718894967b869c0f1d8ff00f",
          "result": "fail"
        },
        "fixed": {
          "checkout": "local_clone",
          "git_head": "68d43a61b552007a718894967b869c0f1d8ff00f_with_fixed_files",
          "result": "pass"
        }
      }
    },
    {
      "blocked_reason": [],
      "bug_id": "17",
      "candidate_validation_report": "docs/experiments/youtubedl17_candidate_validation.md",
      "date": "2026-06-14",
      "decision": "admitted_to_p2p_broad_main",
      "fixed_result": "pass",
      "notes": "Local clone checkout followed the BugsInPy reset/copy-test-file flow after GitHub clone instability was observed in earlier probes. The target pure-utils unittest produced the expected buggy failure and fixed pass. A later project-level P2P-broad run produced 146 retained P2P tests with youtube_dl_dynamic_download_nodeid_exclusion_v1, and four candidate records passed retained-oracle and P2P-broad validation before admission.",
      "p2p_broad_manifest": "data/p2p_scopes/bugsinpy_youtube-dl_17_p2p_broad.json",
      "probe_status": "admitted_p2p_broad_main",
      "project": "youtube-dl",
      "run_command": "python -m unittest -q test.test_utils.TestUtil.test_cli_bool_option",
      "source": "BugsInPy",
      "task_id": "bugsinpy_youtube-dl_17",
      "test_file": "test/test_utils.py",
      "versions": {
        "buggy": {
          "checkout": "local_clone",
          "git_head": "4bf22f7a1014c55e3358b5a419945071b152eafc",
          "result": "fail"
        },
        "fixed": {
          "checkout": "local_clone",
          "git_head": "4bf22f7a1014c55e3358b5a419945071b152eafc_with_fixed_files",
          "result": "pass"
        }
      }
    },
    {
      "blocked_reason": [],
      "bug_id": "2",
      "candidate_validation_report": "docs/experiments/youtubedl2_candidate_validation.md",
      "date": "2026-06-13",
      "decision": "admitted_to_p2p_broad_main",
      "fixed_result": "pass",
      "notes": "Both checkouts completed and the target unittest produced the expected buggy fail and fixed pass. A later approved project-level P2P-broad run produced 147 retained P2P tests, and four candidate records passed retained-oracle and P2P-broad validation before admission.",
      "p2p_broad_manifest": "data/p2p_scopes/bugsinpy_youtube-dl_2_p2p_broad.json",
      "probe_status": "admitted_p2p_broad_main",
      "project": "youtube-dl",
      "run_command": "python -m unittest -q test.test_InfoExtractor.TestInfoExtractor.test_parse_mpd_formats",
      "source": "BugsInPy",
      "task_id": "bugsinpy_youtube-dl_2",
      "test_file": "test/test_InfoExtractor.py",
      "versions": {
        "buggy": {
          "checkout": "completed",
          "git_head": "84f085d4b",
          "result": "fail"
        },
        "fixed": {
          "checkout": "completed",
          "git_head": "84f085d4b",
          "result": "pass"
        }
      }
    },
    {
      "blocked_reason": [],
      "bug_id": "20",
      "candidate_validation_report": "docs/experiments/youtubedl20_candidate_validation.md",
      "date": "2026-06-14",
      "decision": "admitted_to_p2p_broad_main",
      "fixed_result": "pass",
      "notes": "Local clone checkout followed the BugsInPy reset/copy-test-file flow. The target pure-utils unittest produced the expected buggy failure and fixed pass. A later project-level P2P-broad run produced 142 retained P2P tests with youtube_dl_dynamic_download_nodeid_exclusion_v1, and four candidate records passed retained-oracle and P2P-broad validation before admission.",
      "p2p_broad_manifest": "data/p2p_scopes/bugsinpy_youtube-dl_20_p2p_broad.json",
      "probe_status": "admitted_p2p_broad_main",
      "project": "youtube-dl",
      "run_command": "python -m unittest -q test.test_utils.TestUtil.test_get_element_by_attribute",
      "source": "BugsInPy",
      "task_id": "bugsinpy_youtube-dl_20",
      "test_file": "test/test_utils.py",
      "versions": {
        "buggy": {
          "checkout": "local_clone",
          "git_head": "b6c9fe416243373bcb59eb8aa5ef0baca8f3c97c",
          "result": "fail"
        },
        "fixed": {
          "checkout": "local_clone",
          "git_head": "b6c9fe416243373bcb59eb8aa5ef0baca8f3c97c_with_fixed_files",
          "result": "pass"
        }
      }
    },
    {
      "blocked_reason": [
        "corrected_policy_project_level_p2p_timeout"
      ],
      "bug_id": "3",
      "date": "2026-06-14",
      "decision": "do_not_admit_corrected_policy_p2p_timeout",
      "fixed_result": "pass",
      "notes": "Both checkouts completed and the target unittest produced the expected buggy fail and fixed pass. A corrected project-level P2P-broad retry reused youtube_dl_dynamic_download_nodeid_exclusion_v1 and excluded test.test_download.TestDownload, but the builder still exceeded the 40 minute outer budget and left no manifest. Residual unittest processes were stopped; no task-file downgrade was used.",
      "probe_status": "f2p_established_corrected_policy_p2p_timeout",
      "project": "youtube-dl",
      "run_command": "python -m unittest -q test.test_utils.TestUtil.test_unescape_html",
      "source": "BugsInPy",
      "task_id": "bugsinpy_youtube-dl_3",
      "test_file": "test/test_utils.py",
      "versions": {
        "buggy": {
          "checkout": "completed",
          "git_head": "f5469da9e",
          "result": "fail"
        },
        "fixed": {
          "checkout": "completed",
          "git_head": "f5469da9e",
          "result": "pass"
        }
      }
    },
    {
      "blocked_reason": [],
      "bug_id": "4",
      "candidate_validation_report": "docs/experiments/youtubedl4_candidate_validation.md",
      "date": "2026-06-13",
      "decision": "admitted_to_p2p_broad_main",
      "fixed_result": "pass",
      "notes": "Both checkouts completed and the target unittest produced the expected buggy error and fixed pass. A later project-level P2P-broad run produced 137 retained P2P tests, and four candidate records passed retained-oracle and P2P-broad validation before admission.",
      "p2p_broad_manifest": "data/p2p_scopes/bugsinpy_youtube-dl_4_p2p_broad.json",
      "probe_status": "admitted_p2p_broad_main",
      "project": "youtube-dl",
      "run_command": "python -m unittest -q test.test_jsinterp.TestJSInterpreter.test_call",
      "source": "BugsInPy",
      "task_id": "bugsinpy_youtube-dl_4",
      "test_file": "test/test_jsinterp.py",
      "versions": {
        "buggy": {
          "checkout": "completed",
          "git_head": "bc40b3a5b",
          "result": "fail"
        },
        "fixed": {
          "checkout": "completed",
          "git_head": "bc40b3a5b",
          "result": "pass"
        }
      }
    },
    {
      "blocked_reason": [],
      "bug_id": "43",
      "candidate_validation_report": "docs/experiments/youtubedl43_candidate_validation.md",
      "date": "2026-06-14",
      "decision": "admitted_to_p2p_broad_main",
      "fixed_result": "pass",
      "notes": "Local clone checkout followed the BugsInPy reset/copy-test-file flow. The target pure-utils unittest produced the expected buggy failure and fixed pass. A later project-level P2P-broad run produced 18 retained P2P tests with youtube_dl_dynamic_download_nodeid_exclusion_v1, and four candidate records passed retained-oracle and P2P-broad validation before admission.",
      "p2p_broad_manifest": "data/p2p_scopes/bugsinpy_youtube-dl_43_p2p_broad.json",
      "probe_status": "admitted_p2p_broad_main",
      "project": "youtube-dl",
      "run_command": "python -m unittest -q test.test_utils.TestUtil.test_url_basename",
      "source": "BugsInPy",
      "task_id": "bugsinpy_youtube-dl_43",
      "test_file": "test/test_utils.py",
      "versions": {
        "buggy": {
          "checkout": "local_clone",
          "git_head": "cecaaf3f58ad9f544dbb79af1e565d9353fa2b2d",
          "result": "fail"
        },
        "fixed": {
          "checkout": "local_clone",
          "git_head": "cecaaf3f58ad9f544dbb79af1e565d9353fa2b2d_with_fixed_files",
          "result": "pass"
        }
      }
    },
    {
      "blocked_reason": [],
      "bug_id": "5",
      "candidate_validation_report": "docs/experiments/youtubedl5_candidate_validation.md",
      "date": "2026-06-13",
      "decision": "admitted_to_p2p_broad_main",
      "fixed_result": "pass",
      "notes": "Both checkouts completed and the target unittest produced the expected buggy error and fixed pass. A later approved project-level P2P-broad run produced 128 retained P2P tests, and four candidate records passed retained-oracle and P2P-broad validation before admission.",
      "p2p_broad_manifest": "data/p2p_scopes/bugsinpy_youtube-dl_5_p2p_broad.json",
      "probe_status": "admitted_p2p_broad_main",
      "project": "youtube-dl",
      "run_command": "python -m unittest -q test.test_utils.TestUtil.test_unified_timestamps",
      "source": "BugsInPy",
      "task_id": "bugsinpy_youtube-dl_5",
      "test_file": "test/test_utils.py",
      "versions": {
        "buggy": {
          "checkout": "completed",
          "git_head": "b02b960c6",
          "result": "fail"
        },
        "fixed": {
          "checkout": "completed",
          "git_head": "b02b960c6",
          "result": "pass"
        }
      }
    },
    {
      "blocked_reason": [],
      "bug_id": "6",
      "candidate_validation_report": "docs/experiments/youtubedl6_candidate_validation.md",
      "date": "2026-06-13",
      "decision": "admitted_to_p2p_broad_main",
      "fixed_result": "pass",
      "notes": "Both checkouts completed and the target pure-utils unittest produced the expected buggy fail and fixed pass. A later approved project-level P2P-broad run produced 110 retained P2P tests, and four candidate records passed retained-oracle and P2P-broad validation before admission.",
      "p2p_broad_manifest": "data/p2p_scopes/bugsinpy_youtube-dl_6_p2p_broad.json",
      "probe_status": "admitted_p2p_broad_main",
      "project": "youtube-dl",
      "run_command": "python -m unittest -q test.test_utils.TestUtil.test_parse_dfxp_time_expr",
      "source": "BugsInPy",
      "task_id": "bugsinpy_youtube-dl_6",
      "test_file": "test/test_utils.py",
      "versions": {
        "buggy": {
          "checkout": "completed",
          "git_head": "4f29fa990",
          "result": "fail"
        },
        "fixed": {
          "checkout": "completed",
          "git_head": "4f29fa990",
          "result": "pass"
        }
      }
    },
    {
      "blocked_reason": [],
      "bug_id": "7",
      "date": "2026-06-13",
      "decision": "admitted_to_p2p_broad_main",
      "fixed_result": "pass",
      "notes": "Both checkouts completed and the target pure-utils unittest produced the expected buggy fail and fixed pass. A later approved project-level P2P-broad run produced 108 retained P2P tests, and four candidate records passed retained-oracle and P2P-broad validation before admission.",
      "probe_status": "admitted_p2p_broad_main",
      "project": "youtube-dl",
      "run_command": "python -m unittest -q test.test_utils.TestUtil.test_js_to_json_realworld",
      "source": "BugsInPy",
      "task_id": "bugsinpy_youtube-dl_7",
      "test_file": "test/test_utils.py",
      "versions": {
        "buggy": {
          "checkout": "completed",
          "git_head": "63a649483",
          "result": "fail"
        },
        "fixed": {
          "checkout": "completed",
          "git_head": "63a649483",
          "result": "pass"
        }
      }
    }
  ],
  "schema": "controlled_probe_results.v1"
}
